Metadata-Version: 2.1
Name: recommend_games
Version: 0.0.1
Summary: A small recommendation engine for portfolio
Author: Andrew Rawson
Author-email: Andrew Rawson <arawson@proton.me>
Project-URL: Homepage, https://github.com/omcdrucifer/Recommended-Games
Project-URL: Issues, https://github.com/omcdrucifer/Recommended-Games/issues
Classifier: Programming Language :: Python :: 3
Classifier: License :: OSI Approved :: MIT License
Classifier: Operating System :: OS Independent
Requires-Python: >= 3.12
License-File: LICENSE.md
